temp_logger.py
shed_pi-0.0.1.dist-info/METADATA
shed_pi-0.0.1.dist-info/WHEEL
shed_pi-0.0.1.dist-info/top_level.txt
shed_pi-0.0.1.dist-info/RECORD
