Metadata-Version: 2.1
Name: shed_pi
Version: 0.0.1
Summary: Shed Pi
Author: Aiky30
Project-URL: Homepage, https://github.com/Aiky30/shed-pi
Project-URL: Bug Tracker, https://github.com/Aiky30/shed-pi/issues
Classifier: Programming Language :: Python :: 3
Classifier: License :: OSI Approved :: MIT License
Classifier: Operating System :: OS Independent
Requires-Python: >=3.8
